franca_idl-0.1.11.dist-info/METADATA
franca_idl-0.1.11.dist-info/WHEEL
franca_idl/__init__.py
franca_idl/__init__.pyi
franca_idl/franca_idl.cpython-313t-aarch64-linux-gnu.so
franca_idl/py.typed
franca_idl-0.1.11.dist-info/RECORD
