Metadata-Version: 2.4
Name: franca-idl
Version: 0.1.11
Summary: Franca IDL tooling - Includes a Parser for the implemented subset of FIDL.
Keywords: franca,franca-idl,idl,fidl,parsing
License: MIT
Requires-Python: >=3.8
Project-URL: Repository, https://github.com/TimMeiwald/minimal-fidl
